Basic Codes/prio_4x2encoder/prio_encoder4x2.v
module prio_encoder4x2(
    input [3:0] y,
    output reg [1:0] a
);
always @(y) begin
    casex (y)
    4'b0001: begin a=2'b00;
    end
    4'b001x: begin a=2'b01;
    end
    4'b01xx: begin a=2'b10;
    end
    4'b1xxx: begin a=2'b11;
    end
    endcase
    end
endmodule

Basic Codes/prio_4x2encoder/prio_encoder4x2_tb.v
`include "prio_encoder4x2.v"
`timescale 1ns/1ns

module prio_encoder4x2_tb();
wire [1:0] a;
reg [3:0] y;
prio_encoder4x2 uut(.y(y), .a(a));
initial begin
  $dumpfile("prio_encoder4x2_tb.vcd");
  $dumpvars(0,prio_encoder4x2_tb);
  y=0;
  #20;
  y=4'b0000;
  #10;
  y=4'b0001;
  #10;
  y=4'b0010;
  #10;
  y=4'b0100;
  #10;
  y=4'b0110;
  #10;
  y=4'b1000;
  #10;
  y=4'b1010;
  #10;
  y=4'b0011;
  #10;
  y=4'b1111;
  #10;

end


endmodule

Basic Codes/prio_4x2encoder/prio_encoder4x2_tb.vcd
$date
	Wed Jun 09 20:00:44 2021
$end
$version
	Icarus Verilog
$end
$timescale
	1ns
$end
$scope module prio_encoder4x2_tb $end
$var wire 2 ! a [1:0] $end
$var reg 4 " y [3:0] $end
$scope module uut $end
$var wire 4 # y [3:0] $end
$var reg 2 $ a [1:0] $end
$upscope $end
$upscope $end
$enddefinitions $end
#0
$dumpvars
bx $
b0 #
b0 "
bx !
$end
#30
b0 !
b0 $
b1 "
b1 #
#40
b1 !
b1 $
b10 "
b10 #
#50
b10 !
b10 $
b100 "
b100 #
#60
b110 "
b110 #
#70
b11 !
b11 $
b1000 "
b1000 #
#80
b1010 "
b1010 #
#90
b1 !
b1 $
b11 "
b11 #
#100
b11 !
b11 $
b1111 "
b1111 #
